easy_locust/__init__.py
easy_locust/argument.py
easy_locust/main.py
easy_locust/models.py
easy_locust/web.py
easy_locust/web_util.py
easy_locust/boomer_client/boomer_client.json
easy_locust/boomer_client/boomer_master.py
easy_locust/boomer_client/client_v1
easy_locust/boomer_client/client_v1.go
easy_locust/demo/demo_locustfile.json
easy_locust/demo/demo_pressuretest.xls
easy_locust/static/css/bootstrap-theme.css
easy_locust/static/css/bootstrap-theme.css.map
easy_locust/static/css/bootstrap-theme.min.css
easy_locust/static/css/bootstrap-theme.min.css.map
easy_locust/static/css/bootstrap.css
easy_locust/static/css/bootstrap.css.map
easy_locust/static/css/bootstrap.min.css
easy_locust/static/css/bootstrap.min.css.map
easy_locust/static/css/common.css
easy_locust/static/fonts/glyphicons-halflings-regular.eot
easy_locust/static/fonts/glyphicons-halflings-regular.svg
easy_locust/static/fonts/glyphicons-halflings-regular.ttf
easy_locust/static/fonts/glyphicons-halflings-regular.woff
easy_locust/static/fonts/glyphicons-halflings-regular.woff2
easy_locust/static/js/bootstrap.js
easy_locust/static/js/bootstrap.min.js
easy_locust/static/js/common.js
easy_locust/static/js/jquery-3.5.0.min.js
easy_locust/static/js/npm.js
easy_locust/templates/index.html
easy_locust/util/__init__.py
easy_locust/util/boomer_client.py
easy_locust/util/dealParameter.py
easy_locust/util/exception_handler.py
easy_locust/util/extractExcel.py
easy_locust/util/getToken.py
easy_locust/util/locustFileFactory.py
easy_locust/util/slaveNode.py
easy_locust/util/ssh_agent.py
easy_locust-0.2.1.2.data/data/README.md
easy_locust-0.2.1.2.dist-info/LICENSE
easy_locust-0.2.1.2.dist-info/METADATA
easy_locust-0.2.1.2.dist-info/WHEEL
easy_locust-0.2.1.2.dist-info/entry_points.txt
easy_locust-0.2.1.2.dist-info/top_level.txt
easy_locust-0.2.1.2.dist-info/RECORD
